odoo9_addon_privacy-9.0.1.0.0.99.dev11-nspkg.pth
odoo_addons/privacy/README.rst
odoo_addons/privacy/__init__.py
odoo_addons/privacy/__openerp__.py
odoo_addons/privacy/i18n/fr.po
odoo_addons/privacy/i18n/privacy.pot
odoo_addons/privacy/readme/CONTRIBUTORS.rst
odoo_addons/privacy/readme/DESCRIPTION.rst
odoo_addons/privacy/readme/USAGE.rst
odoo_addons/privacy/security/data_protection.xml
odoo_addons/privacy/static/description/icon.png
odoo_addons/privacy/static/description/icon.svg
odoo_addons/privacy/static/description/index.html
odoo_addons/privacy/views/data_protection_menu_view.xml
odoo9_addon_privacy-9.0.1.0.0.99.dev11.dist-info/METADATA
odoo9_addon_privacy-9.0.1.0.0.99.dev11.dist-info/WHEEL
odoo9_addon_privacy-9.0.1.0.0.99.dev11.dist-info/namespace_packages.txt
odoo9_addon_privacy-9.0.1.0.0.99.dev11.dist-info/top_level.txt
odoo9_addon_privacy-9.0.1.0.0.99.dev11.dist-info/RECORD
