Metadata-Version: 2.1
Name: odoo9-addon-privacy
Version: 9.0.1.0.0.99.dev11
Summary: Provides data privacy and protection features to comply to regulations, such as GDPR.
Home-page: http://www.github.com/OCA/data-protection
Author: Eficent, Odoo Community Association (OCA)
Author-email: support@odoo-community.org
License: AGPL-3
Platform: UNKNOWN
Classifier: Programming Language :: Python
Classifier: Framework :: Odoo
Classifier: License :: OSI Approved :: GNU Affero General Public License v3
Requires-Python: ~=2.7
Requires-Dist: odoo (<9.1a,>=9.0a)
